{
  "accounts": [
    {
      "id": 1,
      "name": "支付宝",
      "type": "cash",
      "description": "电子支付账户",
      "balance": 100,
      "icon": "wezhong.svg"
    },
    {
      "id": 2,
      "name": "微信",
      "type": "credit",
      "description": "电子支付账户",
      "balance": 200,
      "icon": "wezhong.svg"
    },
    {
      "id": 3,
      "name": "现金",
      "type": "investment",
      "description": "实物货币",
      "balance": 0,
      "icon": "wezhong.svg"
    }
  ],
  "transactions": []
}